aiomisc_pytest.py
aiomisc_pytest-1.3.4.dist-info/COPYING
aiomisc_pytest-1.3.4.dist-info/METADATA
aiomisc_pytest-1.3.4.dist-info/WHEEL
aiomisc_pytest-1.3.4.dist-info/entry_points.txt
aiomisc_pytest-1.3.4.dist-info/RECORD
