Metadata-Version: 2.3
Name: aiomisc-pytest
Version: 1.3.4
Summary: pytest integration for aiomisc
License: MIT
Keywords: pytest,aiomisc
Author: Dmitry Orlov
Author-email: me@mosquito.su
Requires-Python: >=3.10,<4.0
Classifier: Environment :: Plugins
Classifier: Framework :: Pytest
Classifier: Intended Audience :: Developers
Classifier: License :: OSI Approved :: Apache Software License
Classifier: License :: OSI Approved :: MIT License
Classifier: Natural Language :: English
Classifier: Operating System :: MacOS
Classifier: Operating System :: Microsoft
Classifier: Operating System :: POSIX
Classifier: Programming Language :: Python :: 3
Classifier: Programming Language :: Python :: 3.10
Classifier: Programming Language :: Python :: 3.11
Classifier: Programming Language :: Python :: 3.12
Classifier: Programming Language :: Python :: 3.13
Classifier: Programming Language :: Python :: 3 :: Only
Classifier: Topic :: Software Development
Classifier: Topic :: Software Development :: Libraries
Requires-Dist: aiomisc (>=17)
Requires-Dist: pytest (>=8.4,<9.0)
